pytsdatasets/__init__.py
pytsdatasets/pytsdatasets.py
pytsdatasets/data/airpassengers.csv
pytsdatasets/data/co2.csv
pytsdatasets/data/globaltemp.csv
pytsdatasets/data/h02.csv
pytsdatasets/data/jj.csv
pytsdatasets/data/uschange.csv
pytsdatasets-1.0.dist-info/LICENSE
pytsdatasets-1.0.dist-info/METADATA
pytsdatasets-1.0.dist-info/WHEEL
pytsdatasets-1.0.dist-info/top_level.txt
pytsdatasets-1.0.dist-info/RECORD
