Metadata-Version: 2.1
Name: pytsdatasets
Version: 1.0
Summary: A python package that provides some time series datasets available R distribution and in astsa R package.
Home-page: https://github.com/mjuez/pytsdatasets
Author: Mario Juez-Gil
Author-email: mariojg@ubu.es
License: GPLv3
Download-URL: https://github.com/mjuez/pytsdatasets/archive/v1_0.tar.gz
Platform: UNKNOWN
Classifier: Development Status :: 5 - Production/Stable
Classifier: Intended Audience :: Developers 
Classifier: Intended Audience :: Education 
Classifier: Intended Audience :: Science/Research 
Classifier: Topic :: Scientific/Engineering
Classifier: Topic :: Education
Classifier: Topic :: Database
Classifier: License :: OSI Approved :: GNU General Public License v3 (GPLv3)
Classifier: Programming Language :: Python :: 3
Classifier: Programming Language :: Python :: 3.6
Classifier: Programming Language :: Python :: 3.7
Classifier: Programming Language :: Python :: 3.8
Requires-Dist: pandas (==1.1.2)
